zalfmas_common/__init__.py
zalfmas_common/climate/__init__.py
zalfmas_common/climate/common_climate_data_capnp_impl.py
zalfmas_common/climate/csv_file_based.py
zalfmas_common/common.py
zalfmas_common/csv.py
zalfmas_common/geo.py
zalfmas_common/model/__init__.py
zalfmas_common/model/monica_io.py
zalfmas_common/rect_ascii_grid_management.py
zalfmas_common/service.py
zalfmas_common/soil/__init__.py
zalfmas_common/soil/soil_io.py
zalfmas_common-0.1.38.dist-info/METADATA
zalfmas_common-0.1.38.dist-info/WHEEL
zalfmas_common-0.1.38.dist-info/licenses/LICENSE
zalfmas_common-0.1.38.dist-info/RECORD
