Metadata-Version: 2.4
Name: zalfmas-common
Version: 0.1.38
Summary: Common code for ZALF MAS projects
License-File: LICENSE
Author: Michael Berg-Mohnicke
Author-email: michael.berg@zalf.de
Requires-Python: >=3.10,<3.14
Classifier: Programming Language :: Python :: 3
Classifier: Programming Language :: Python :: 3.10
Classifier: Programming Language :: Python :: 3.11
Classifier: Programming Language :: Python :: 3.12
Classifier: Programming Language :: Python :: 3.13
Requires-Dist: pandas (>=2.2.2,<4.0.0)
Requires-Dist: psutil (>=7.0.0,<8.0.0)
Requires-Dist: pycapnp (>=2.1.0,<3.0.0)
Requires-Dist: pyproj (>=3.6.1,<4.0.0)
Requires-Dist: pysodium (>=0.7.17,<0.8.0)
Requires-Dist: scipy (>=1.13.1,<2.0.0)
Requires-Dist: tomli (>=2.3.0,<3.0.0)
Requires-Dist: tomlkit (>=0.13.2,<0.14.0)
Requires-Dist: zalfmas-capnp-schemas (>=0.1.41,<0.2.0)
